syntax/__init__.py
syntax/_utils/__init__.py
syntax/_utils/misc.py
syntax/slide/__init__.py
syntax/slide/slide.py
syntax/slide/utils.py
syntax/transformers/__init__.py
syntax/transformers/base.py
syntax/transformers/utils.py
syntax/transformers/tiling/__init__.py
syntax/transformers/tiling/tiling.py
syntax/transformers/tiling/utils.py
syntax/transformers/tissue_mask/__init__.py
syntax/transformers/tissue_mask/mask.py
syntax/transformers/tissue_mask/otsu.py
compay_syntax-0.4.1.dist-info/LICENSE
compay_syntax-0.4.1.dist-info/METADATA
compay_syntax-0.4.1.dist-info/WHEEL
compay_syntax-0.4.1.dist-info/top_level.txt
compay_syntax-0.4.1.dist-info/RECORD
