Metadata-Version: 2.1
Name: compay-syntax
Version: 0.4.1
Summary: Syntax - the arrangement of whole-slide-images and their image tiles to create well-formed computational pathology pipelines.
Home-page: https://github.com/jgamper/compay-syntax
Author: Jevgenij Gamper & Peter Byfield
Author-email: jevgenij.gamper5@gmail.com
License: UNKNOWN
Platform: UNKNOWN
Classifier: Programming Language :: Python :: 3.6
Requires-Dist: numpy
Requires-Dist: openslide-python
Requires-Dist: matplotlib
Requires-Dist: jupyter-client
Requires-Dist: jupyter-core
Requires-Dist: Pillow
Requires-Dist: typeguard
Requires-Dist: pandas
Requires-Dist: scikit-image
